[{"Title":"सेक्सी लड़की घोड़ी बनकर चुदी","thumbnail":"https://www.freesexkahani.com/wp-content/uploads/2022/02/bf-sex-video_thumb2-300x162.jpg","author":{"name":"Guruji","href":"https://www.freesexkahani.com/author/guruji/"},"date":"04-02-2022","views":"1,453","description":"","href":"https://www.freesexkahani.com/videos/bf-sex-video/","tags":[{"name":"Desi hindi Xxx","href":"https://www.freesexkahani.com/videos/tag/desi-hindi-xxx/"},{"name":"Hindi Chudai Video","href":"https://www.freesexkahani.com/videos/tag/hindi-chudai-video/"},{"name":"hotel sex video","href":"https://www.freesexkahani.com/videos/tag/hotel-sex-video/"}]},{"Title":"अकेली हॉट गर्ल चुदाई के लिए तड़प रही है","thumbnail":"https://www.freesexkahani.com/wp-content/uploads/2021/12/sexy-ladki-ki-chut-video_thumb2-300x169.jpg","author":{"name":"Guruji","href":"https://www.freesexkahani.com/author/guruji/"},"date":"03-02-2022","views":"1,147","description":"","href":"https://www.freesexkahani.com/videos/sexy-ladki-ki-chut-video/","tags":[{"name":"College Girl Video","href":"https://www.freesexkahani.com/videos/tag/college-girl-video/"},{"name":"Desi hindi Xxx","href":"https://www.freesexkahani.com/videos/tag/desi-hindi-xxx/"},{"name":"HD Video","href":"https://www.freesexkahani.com/videos/tag/hd-video/"},{"name":"Sexy Hindi Film","href":"https://www.freesexkahani.com/videos/tag/sexy-hindi-film/"}]},{"Title":"बीवी की गांड में उंगली का शौकीन पति","thumbnail":"https://www.freesexkahani.com/wp-content/uploads/2021/12/moti-gand-sex-video_thumb2-168x300.jpg","author":{"name":"Guruji","href":"https://www.freesexkahani.com/author/guruji/"},"date":"02-02-2022","views":"729","description":"","href":"https://www.freesexkahani.com/videos/moti-gand-sex-video/","tags":[{"name":"Desi hindi Xxx","href":"https://www.freesexkahani.com/videos/tag/desi-hindi-xxx/"},{"name":"Desi Indian MMS","href":"https://www.freesexkahani.com/videos/tag/desi-indian-mms/"},{"name":"HD Video","href":"https://www.freesexkahani.com/videos/tag/hd-video/"},{"name":"Hindi Sex Video","href":"https://www.freesexkahani.com/videos/tag/hindi-sex-video/"},{"name":"Sexy Hindi Film","href":"https://www.freesexkahani.com/videos/tag/sexy-hindi-film/"},{"name":"Wife Sex Video","href":"https://www.freesexkahani.com/videos/tag/wife-sex-video/"}]},{"Title":"हिजाब पहने लड़की ने सगे भाई का लंड खाया","thumbnail":"https://www.freesexkahani.com/wp-content/uploads/2022/01/porn-hijab-xxx-video_thumb2-300x169.jpg","author":{"name":"Guruji","href":"https://www.freesexkahani.com/author/guruji/"},"date":"01-02-2022","views":"4,108","description":"","href":"https://www.freesexkahani.com/videos/porn-hijab-xxx-video/","tags":[{"name":"College Girl Video","href":"https://www.freesexkahani.com/videos/tag/college-girl-video/"},{"name":"HD Video","href":"https://www.freesexkahani.com/videos/tag/hd-video/"},{"name":"Position 69 Sex","href":"https://www.freesexkahani.com/videos/tag/position-69-sex/"},{"name":"Xxx Video","href":"https://www.freesexkahani.com/videos/tag/xxx-video/"}]},{"Title":"सेक्सी बीवी को गर्म करके गांड मारी","thumbnail":"https://www.freesexkahani.com/wp-content/uploads/2022/01/husband-and-wife-xxx_thumb2-300x138.jpg","author":{"name":"Guruji","href":"https://www.freesexkahani.com/author/guruji/"},"date":"31-01-2022","views":"2,408","description":"","href":"https://www.freesexkahani.com/videos/husband-and-wife-xxx/","tags":[{"name":"Hindi Chudai Video","href":"https://www.freesexkahani.com/videos/tag/hindi-chudai-video/"},{"name":"Indian BF","href":"https://www.freesexkahani.com/videos/tag/indian-bf/"},{"name":"Position 69 Sex","href":"https://www.freesexkahani.com/videos/tag/position-69-sex/"},{"name":"Wife Sex Video","href":"https://www.freesexkahani.com/videos/tag/wife-sex-video/"},{"name":"Xnxx Hindi Video","href":"https://www.freesexkahani.com/videos/tag/xnxx-hindi-video/"}]},{"Title":"गदराई पंजाबन लड़की का नंगा नाच","thumbnail":"https://www.freesexkahani.com/wp-content/uploads/2021/12/punjabi-girl-sex-video_thumb2-168x300.jpg","author":{"name":"Guruji","href":"https://www.freesexkahani.com/author/guruji/"},"date":"30-01-2022","views":"2,185","description":"","href":"https://www.freesexkahani.com/videos/punjabi-girl-sex-video/","tags":[{"name":"College Girl Video","href":"https://www.freesexkahani.com/videos/tag/college-girl-video/"},{"name":"Desi Indian MMS","href":"https://www.freesexkahani.com/videos/tag/desi-indian-mms/"},{"name":"HD Video","href":"https://www.freesexkahani.com/videos/tag/hd-video/"},{"name":"Hindi Sex Video","href":"https://www.freesexkahani.com/videos/tag/hindi-sex-video/"},{"name":"Sexy Hindi Film","href":"https://www.freesexkahani.com/videos/tag/sexy-hindi-film/"}]},{"Title":"सौतेले भाई बहन की दमदार चुदाई","thumbnail":"https://www.freesexkahani.com/wp-content/uploads/2021/12/bhai-ne-bahan-ko-choda_thumb2-300x169.jpg","author":{"name":"Guruji","href":"https://www.freesexkahani.com/author/guruji/"},"date":"29-01-2022","views":"37,507","description":"","href":"https://www.freesexkahani.com/videos/bhai-ne-bahan-ko-choda/","tags":[{"name":"Desi hindi Xxx","href":"https://www.freesexkahani.com/videos/tag/desi-hindi-xxx/"},{"name":"Hindi Sex Video","href":"https://www.freesexkahani.com/videos/tag/hindi-sex-video/"},{"name":"Indian Web Series","href":"https://www.freesexkahani.com/videos/tag/indian-web-series/"},{"name":"Sexy Hindi Film","href":"https://www.freesexkahani.com/videos/tag/sexy-hindi-film/"},{"name":"Xxx Video","href":"https://www.freesexkahani.com/videos/tag/xxx-video/"}]},{"Title":"गर्म बंगाली भाभी देवर से चुद गयी","thumbnail":"https://www.freesexkahani.com/wp-content/uploads/2021/12/bengali-bhabhi-ki-chudai-video_thumb2-300x169.jpg","author":{"name":"Guruji","href":"https://www.freesexkahani.com/author/guruji/"},"date":"28-01-2022","views":"3,295","description":"","href":"https://www.freesexkahani.com/videos/bengali-bhabhi-ki-chudai-video/","tags":[{"name":"Desi Indian MMS","href":"https://www.freesexkahani.com/videos/tag/desi-indian-mms/"},{"name":"Hindi Sex Video","href":"https://www.freesexkahani.com/videos/tag/hindi-sex-video/"},{"name":"Sexy Hindi Film","href":"https://www.freesexkahani.com/videos/tag/sexy-hindi-film/"},{"name":"Xxx Video","href":"https://www.freesexkahani.com/videos/tag/xxx-video/"}]},{"Title":"लंड टट्टे चूस चाट कर वीर्य मुंह में लिया","thumbnail":"https://www.freesexkahani.com/wp-content/uploads/2021/12/sexy-indian-bhabhi-oral-video_thumb2-300x169.jpg","author":{"name":"Guruji","href":"https://www.freesexkahani.com/author/guruji/"},"date":"27-01-2022","views":"1,352","description":"","href":"https://www.freesexkahani.com/videos/sexy-indian-bhabhi-oral-video/","tags":[{"name":"HD Video","href":"https://www.freesexkahani.com/videos/tag/hd-video/"},{"name":"Hindi Sex Video","href":"https://www.freesexkahani.com/videos/tag/hindi-sex-video/"},{"name":"Indian BF","href":"https://www.freesexkahani.com/videos/tag/indian-bf/"},{"name":"Wife Sex Video","href":"https://www.freesexkahani.com/videos/tag/wife-sex-video/"}]},{"Title":"बड़ी चूचियों वाली बंगालन भाभी चुद गयी","thumbnail":"https://www.freesexkahani.com/wp-content/uploads/2021/12/big-boobs-sex-video_thumb1-300x218.jpg","author":{"name":"Guruji","href":"https://www.freesexkahani.com/author/guruji/"},"date":"26-01-2022","views":"3,338","description":"","href":"https://www.freesexkahani.com/videos/big-boobs-sex-video/","tags":[{"name":"Desi hindi Xxx","href":"https://www.freesexkahani.com/videos/tag/desi-hindi-xxx/"},{"name":"HD Video","href":"https://www.freesexkahani.com/videos/tag/hd-video/"},{"name":"Indian BF","href":"https://www.freesexkahani.com/videos/tag/indian-bf/"},{"name":"Xxx Video","href":"https://www.freesexkahani.com/videos/tag/xxx-video/"}]}]